{
  "id": [
    "t_water_dp",
    "t_swater_dp"
  ],
  "fg": [
    "t_swater_dp"
  ],
  "rotates": false,
  "multitile": true,
  "additional_tiles": [
    { "id": "center", "fg": [ "t_swater_dp" ], "bg": [ "t_dirt" ] },
    { "id": "corner", "fg": [ "t_swater_dp_2" ], "bg": [ "t_dirt" ] },
    { "id": "edge", "fg": [ "t_swater_dp_3" ], "bg": [ "t_dirt" ] },
    { "id": "end_piece", "fg": [ "t_swater_dp_4" ], "bg": [ "t_dirt" ] },
    { "id": "unconnected", "fg": [ "t_swater_dp_5" ], "bg": [ "t_dirt" ] }
  ],
  "bg": [
    "t_dirt"
  ]
}
