{
  "id": "t_wall_resin",
  "fg": "t_wall_resin_unconnected",
  "bg": "",
  "multitile": true,
  "additional_tiles": [
    { "id": "center", "fg": "t_wall_resin_center", "bg": "" },
    {
      "id": "corner",
      "fg": [ "t_wall_resin_corner_nw", "t_wall_resin_corner_sw", "t_wall_resin_corner_se", "t_wall_resin_corner_ne" ],
      "bg": ""
    },
    {
      "id": "t_connection",
      "fg": [
        "t_wall_resin_t_connection_n",
        "t_wall_resin_t_connection_w",
        "t_wall_resin_t_connection_s",
        "t_wall_resin_t_connection_e"
      ],
      "bg": ""
    },
    { "id": "edge", "fg": [ "t_wall_resin_edge_ns", "t_wall_resin_edge_ew" ], "bg": "" },
    {
      "id": "end_piece",
      "fg": [ "t_wall_resin_end_piece_n", "t_wall_resin_end_piece_w", "t_wall_resin_end_piece_s", "t_wall_resin_end_piece_e" ],
      "bg": ""
    },
    { "id": "unconnected", "fg": [ "t_wall_resin_unconnected", "t_wall_resin_unconnected" ], "bg": "t_dirt" }
  ]
}
